codegenpt/__init__.py
codegenpt/cli.py
codegenpt/codegenpt_directory.py
codegenpt/codegenpt_file.py
codegenpt/codegenpt_instructions.py
codegenpt/commands/__init__.py
codegenpt/commands/command.py
codegenpt/commands/commands.py
codegenpt/commands/include.py
codegenpt/dependency_batch-old copy.py
codegenpt/dependency_batch.py
codegenpt/dependency_batch.py.codegenpt
codegenpt/filesystem/__init__.py
codegenpt/filesystem/file_discovery.py
codegenpt/generators/__init__.py
codegenpt/generators/directory_generator.py
codegenpt/generators/file_generator.py
codegenpt/llm/__init__.py
codegenpt/llm/llm.py
codegenpt-0.8.1.dist-info/LICENSE
codegenpt-0.8.1.dist-info/METADATA
codegenpt-0.8.1.dist-info/WHEEL
codegenpt-0.8.1.dist-info/entry_points.txt
codegenpt-0.8.1.dist-info/RECORD
